tinybid/__init__.py
tinybid/tinybid.py
tinybid-0.2.0.dist-info/LICENSE
tinybid-0.2.0.dist-info/METADATA
tinybid-0.2.0.dist-info/WHEEL
tinybid-0.2.0.dist-info/top_level.txt
tinybid-0.2.0.dist-info/RECORD
