Metadata-Version: 2.1
Name: tinybid
Version: 0.2.0
Summary: Minimal pure-Python library that implements a basic single-item first-price auction via a secure multi-party computation (MPC) protocol.
Author: Nillion
Author-email: engineering@nillion.com
License: MIT
Project-URL: Repository, https://github.com/nillion-oss/tinybid
Project-URL: Documentation, https://tinybid.readthedocs.io
Requires-Python: >=3.7
License-File: LICENSE
Requires-Dist: bitlist ~=1.2
Requires-Dist: modulo ~=2.1
Requires-Dist: tinynmc ~=0.2
Provides-Extra: coveralls
Requires-Dist: coveralls ~=3.3.1 ; extra == 'coveralls'
Provides-Extra: docs
Requires-Dist: toml ~=0.10.2 ; extra == 'docs'
Requires-Dist: sphinx ~=4.2.0 ; extra == 'docs'
Requires-Dist: sphinx-rtd-theme ~=1.0.0 ; extra == 'docs'
Requires-Dist: sphinx-autodoc-typehints ~=1.12.0 ; extra == 'docs'
Provides-Extra: lint
Requires-Dist: pylint ~=2.17.0 ; extra == 'lint'
Provides-Extra: publish
Requires-Dist: build ~=0.10 ; extra == 'publish'
Requires-Dist: twine ~=4.0 ; extra == 'publish'
Provides-Extra: test
Requires-Dist: pytest ~=7.2 ; extra == 'test'
Requires-Dist: pytest-cov ~=4.0 ; extra == 'test'
